parse_audits/__init__.py
parse_audits/__main__.py
parse_audits/models.py
parse_audits/parsers.py
parse_audits/utils.py
parser_cli/__init__.py
parser_cli/cli.py
parse_audits-2.7.3.dist-info/entry_points.txt
parse_audits-2.7.3.dist-info/LICENSE.txt
parse_audits-2.7.3.dist-info/WHEEL
parse_audits-2.7.3.dist-info/METADATA
parse_audits-2.7.3.dist-info/RECORD
