Metadata-Version: 2.1
Name: parse-audits
Version: 2.7.3
Summary: A library and tool to parse ClearQuest AuditTrail files to an easier-to-use format.
Home-page: https://github.com/harmony5/parse_audits
License: MIT
Author: harmony5
Author-email: jeancgo@pm.me
Requires-Python: >=3.8,<4.0
Classifier: License :: OSI Approved :: MIT License
Classifier: Programming Language :: Python :: 3
Classifier: Programming Language :: Python :: 3.8
Classifier: Programming Language :: Python :: 3.9
Requires-Dist: pandas (>=1.3.1,<2.0.0)
Requires-Dist: regex (>=2021.8.3,<2022.0.0)
Requires-Dist: typer (>=0.3.2,<0.4.0)
Project-URL: Bug Tracker, https://github.com/harmony5/parse_audits/issues
Project-URL: Repository, https://github.com/harmony5/parse_audits
